arbi/__init__.py
arbi/main.py
arbi/ai/__init__.py
arbi/ai/feature_engineering.py
arbi/ai/feature_engineering_v2.py
arbi/ai/feature_schema.json
arbi/ai/inference.py
arbi/ai/inference_v2.py
arbi/ai/models.py
arbi/ai/monitoring.py
arbi/ai/real_data_integration.py
arbi/ai/registry.py
arbi/ai/training.py
arbi/ai/training_v2.py
arbi/api/__init__.py
arbi/api/server.py
arbi/config/__init__.py
arbi/config/settings.py
arbi/config/settings_new.py
arbi/config/settings_old.py
arbi/core/__init__.py
arbi/core/backtest.py
arbi/core/data_feed.py
arbi/core/execution.py
arbi/core/marketdata.py
arbi/core/pipeline.py
arbi/core/portfolio.py
arbi/core/risk.py
arbi/core/signal.py
arbi/core/storage.py
arbi/tests/__init__.py
arbi/tests/test_data_feed.py
arbi/ui/__init__.py
arbi/ui/dashboard.py
trading_bot_ml-1.0.0.dist-info/METADATA
trading_bot_ml-1.0.0.dist-info/WHEEL
trading_bot_ml-1.0.0.dist-info/entry_points.txt
trading_bot_ml-1.0.0.dist-info/top_level.txt
trading_bot_ml-1.0.0.dist-info/RECORD
